Metadata-Version: 1.0
Name: bioscraping
Version: 0.0.2
Summary: Scrape biological data from websites
Home-page: https://github.com/mlovci/bioscraping
Author: Michael T Lovci
Author-email: Michael.T.Lovci@gmail.com
License: MIT
Keywords: scraping,biological data
Platform: UNKNOWN
